sitesniffer/__init__.py
sitesniffer/_sitesniffer.py
sitesniffer/data.py
sitesniffer/exceptions.py
sitesniffer-0.4.1.dist-info/LICENCE
sitesniffer-0.4.1.dist-info/METADATA
sitesniffer-0.4.1.dist-info/WHEEL
sitesniffer-0.4.1.dist-info/top_level.txt
sitesniffer-0.4.1.dist-info/RECORD
