Metadata-Version: 2.1
Name: sitesniffer
Version: 0.4.1
Summary: This is a Python script that can extract various information about a website, including its IP address, SSL certificate information, domain information, page load time, and other useful insights.
Home-page: https://github.com/thisisjsimon/SiteSniffer
Author: Jonah Simon
Author-email: thisisjsimon.github@gmail.com
License: MIT
Keywords: sniffing,site sniffing,website sniffing,IP address,SSL certificate,domain,website
Requires-Python: >=3.11
License-File: LICENCE
Requires-Dist: python-whois
Requires-Dist: bs4
Requires-Dist: idna
Requires-Dist: requests
Provides-Extra: dev
Requires-Dist: pytest ; extra == 'dev'
Requires-Dist: twine ; extra == 'dev'
